<annotation>
	<folder>images</folder>
	<filename>image_4.jpg</filename>
	<path>C:\Users\sandh.SHRIHARI\OneDrive\Desktop\Data_science\YOLO\dataset\images\image_4.jpg</path>
	<source>
		<database>Unknown</database>
	</source>
	<size>
		<width>6609</width>
		<height>4406</height>
		<depth>3</depth>
	</size>
	<segmented>0</segmented>
	<object>
		<name>person</name>
		<pose>Unspecified</pose>
		<truncated>0</truncated>
		<difficult>0</difficult>
		<bndbox>
			<xmin>978</xmin>
			<ymin>721</ymin>
			<xmax>2216</xmax>
			<ymax>4026</ymax>
		</bndbox>
	</object>
	<object>
		<name>person</name>
		<pose>Unspecified</pose>
		<truncated>0</truncated>
		<difficult>0</difficult>
		<bndbox>
			<xmin>2059</xmin>
			<ymin>1326</ymin>
			<xmax>2902</xmax>
			<ymax>3150</ymax>
		</bndbox>
	</object>
	<object>
		<name>person</name>
		<pose>Unspecified</pose>
		<truncated>0</truncated>
		<difficult>0</difficult>
		<bndbox>
			<xmin>2854</xmin>
			<ymin>1659</ymin>
			<xmax>3873</xmax>
			<ymax>2988</ymax>
		</bndbox>
	</object>
	<object>
		<name>person</name>
		<pose>Unspecified</pose>
		<truncated>0</truncated>
		<difficult>0</difficult>
		<bndbox>
			<xmin>4073</xmin>
			<ymin>1779</ymin>
			<xmax>4916</xmax>
			<ymax>2783</ymax>
		</bndbox>
	</object>
	<object>
		<name>laptop</name>
		<pose>Unspecified</pose>
		<truncated>0</truncated>
		<difficult>0</difficult>
		<bndbox>
			<xmin>4216</xmin>
			<ymin>2164</ymin>
			<xmax>5483</xmax>
			<ymax>3112</ymax>
		</bndbox>
	</object>
</annotation>
