<annotation>
	<folder>images</folder>
	<filename>image_72.jpg</filename>
	<path>C:\Users\sandh.SHRIHARI\OneDrive\Desktop\Data_science\YOLO\dataset\images\image_72.jpg</path>
	<source>
		<database>Unknown</database>
	</source>
	<size>
		<width>3306</width>
		<height>4959</height>
		<depth>3</depth>
	</size>
	<segmented>0</segmented>
	<object>
		<name>person</name>
		<pose>Unspecified</pose>
		<truncated>0</truncated>
		<difficult>0</difficult>
		<bndbox>
			<xmin>1911</xmin>
			<ymin>1679</ymin>
			<xmax>2683</xmax>
			<ymax>4662</ymax>
		</bndbox>
	</object>
	<object>
		<name>person</name>
		<pose>Unspecified</pose>
		<truncated>0</truncated>
		<difficult>0</difficult>
		<bndbox>
			<xmin>1539</xmin>
			<ymin>1656</ymin>
			<xmax>1933</xmax>
			<ymax>4434</ymax>
		</bndbox>
	</object>
	<object>
		<name>person</name>
		<pose>Unspecified</pose>
		<truncated>0</truncated>
		<difficult>0</difficult>
		<bndbox>
			<xmin>1072</xmin>
			<ymin>1595</ymin>
			<xmax>1578</xmax>
			<ymax>4456</ymax>
		</bndbox>
	</object>
</annotation>
